mypyc_aot/__init__.py
mypyc_aot/compiler.py
mypyc_aot/ipy_integration.py
mypyc_aot/mypyc_aot.py
mypyc_aot/py.typed
mypyc_aot/unix_compiler_util.py
mypyc_aot/tests/__init__.py
mypyc_aot/tests/test_aot_perf.py
mypyc_aot/tests/test_class_wrapper.py
mypyc_aot-1.0.3.dist-info/licenses/LICENSE
mypyc_aot-1.0.3.dist-info/METADATA
mypyc_aot-1.0.3.dist-info/WHEEL
mypyc_aot-1.0.3.dist-info/top_level.txt
mypyc_aot-1.0.3.dist-info/RECORD
