Metadata-Version: 2.4
Name: mypyc-aot
Version: 1.0.3
Summary: A performance optimization library based on mypyc, similar to numba but supporting accelerating general Python code.
Author: ekcbw
License-Expression: MIT
Project-URL: Homepage, https://github.com/ekcbw/mypyc-aot
Keywords: mypyc,mypy,aot,speedup,performance
Classifier: Programming Language :: Python :: 3
Classifier: Topic :: Software Development :: Compilers
License-File: LICENSE
Requires-Dist: mypy
Requires-Dist: setuptools
Dynamic: license-file
